{
  "chain": "Tron",
  "address": "TGE94jU39ithtHbrYAQJRTcvv785riPLdy",
  "direction": "inflow",
  "hops_requested": {
    "inflow": 1,
    "outflow": 0
  },
  "parameters": {
    "max_nodes_per_hop": 100,
    "min_timestamp_ms": 1645856335797,
    "max_timestamp_ms": 1772000335797
  },
  "timestamp": "2026-02-25T14:19:00.309702",
  "execution_time": "0:00:04.511955",
  "graph_data": {
    "code": 0,
    "data": {
      "task_id": 25948,
      "address": "TGE94jU39ithtHbrYAQJRTcvv785riPLdy",
      "inflow_total_amount": 270602.8836,
      "outflow_total_amount": 270602.8836,
      "tags": [
        {
          "address": "TGE94jU39ithtHbrYAQJRTcvv785riPLdy",
          "chain_name": "Tron",
          "primary_category": "Other Entities",
          "secondary_category": "Wallet Address",
          "tertiary_category": "Huionepay",
          "quaternary_category": "huionepay-withdrawal-level1",
          "risk_level": "low",
          "priority": 4
        }
      ],
      "paths": [
        {
          "direction": -1,
          "request_id": 173378,
          "query_address": "TGE94jU39ithtHbrYAQJRTcvv785riPLdy",
          "chain_name": "Tron",
          "token": "usdt",
          "opponent_address": "TL1N**************************NgQy",
          "hops": 1,
          "path": [
            {
              "address": "TL1N**************************NgQy",
              "chain_name": "",
              "token": "",
              "deep": 0,
              "pre_address": "null",
              "tags": [
                {
                  "address": "TL1N**************************NgQy",
                  "chain_name": "Tron",
                  "primary_category": "Sanctions",
                  "secondary_category": "Prohibited Entity",
                  "tertiary_category": "Huionepay",
                  "quaternary_category": "huionepay-deposit",
                  "risk_level": "high",
                  "priority": 1
                }
              ],
              "amount": 0,
              "flag": 1,
              "last_closed_timestamp": 0
            },
            {
              "address": "TGE9**************************PLdy",
              "chain_name": "",
              "token": "",
              "deep": 0,
              "pre_address": "TL1N**************************NgQy",
              "tags": [
                {
                  "address": "TGE9**************************PLdy",
                  "chain_name": "Tron",
                  "primary_category": "Other Entities",
                  "secondary_category": "Wallet Address",
                  "tertiary_category": "Huionepay",
                  "quaternary_category": "huionepay-withdrawal-level1",
                  "risk_level": "low",
                  "priority": 4
                }
              ],
              "amount": 700,
              "flag": 0,
              "last_closed_timestamp": 1739006160000
            }
          ],
          "tags": [
            {
              "address": "TL1NWD6ckwbMAZ5uURzaYsYC43hBjWNgQy",
              "chain_name": "Tron",
              "primary_category": "Sanctions",
              "secondary_category": "Prohibited Entity",
              "tertiary_category": "Huionepay",
              "quaternary_category": "huionepay-deposit",
              "risk_level": "high",
              "priority": 1
            }
          ]
        },
        {
          "direction": -1,
          "request_id": 173378,
          "query_address": "TGE94jU39ithtHbrYAQJRTcvv785riPLdy",
          "chain_name": "Tron",
          "token": "usdt",
          "opponent_address": "TUFd**************************hs54",
          "hops": 1,
          "path": [
            {
              "address": "TUFd**************************hs54",
              "chain_name": "",
              "token": "",
              "deep": 0,
              "pre_address": "null",
              "tags": [
                {
                  "address": "TUFd**************************hs54",
                  "chain_name": "Tron",
                  "primary_category": "Other Entities",
                  "secondary_category": "Wallet Address",
                  "tertiary_category": "Huionepay",
                  "quaternary_category": "huionepay-withdrawal-level1",
                  "risk_level": "low",
                  "priority": 4
                },
                {
                  "address": "TUFd**************************hs54",
                  "chain_name": "Tron",
                  "primary_category": "Sanctions",
                  "secondary_category": "Prohibited Entity",
                  "tertiary_category": "Huionepay",
                  "quaternary_category": "huionepay-deposit",
                  "risk_level": "high",
                  "priority": 1
                },
                {
                  "address": "TUFd**************************hs54",
                  "chain_name": "Tron",
                  "primary_category": "Cybercrime",
                  "secondary_category": "Black/Grey Industry",
                  "tertiary_category": "Fraudsters",
                  "quaternary_category": "fraudsters-address",
                  "risk_level": "high",
                  "priority": 4
                }
              ],
              "amount": 0,
              "flag": 9,
              "last_closed_timestamp": 0
            },
            {
              "address": "TGE9**************************PLdy",
              "chain_name": "",
              "token": "",
              "deep": 0,
              "pre_address": "TUFd**************************hs54",
              "tags": [
                {
                  "address": "TGE9**************************PLdy",
                  "chain_name": "Tron",
                  "primary_category": "Other Entities",
                  "secondary_category": "Wallet Address",
                  "tertiary_category": "Huionepay",
                  "quaternary_category": "huionepay-withdrawal-level1",
                  "risk_level": "low",
                  "priority": 4
                }
              ],
              "amount": 9.7,
              "flag": 0,
              "last_closed_timestamp": 1739467860000
            }
          ],
          "tags": [
            {
              "address": "TUFdgdFjCoQefqNfamYPuyDsRkv471hs54",
              "chain_name": "Tron",
              "primary_category": "Other Entities",
              "secondary_category": "Wallet Address",
              "tertiary_category": "Huionepay",
              "quaternary_category": "huionepay-withdrawal-level1",
              "risk_level": "low",
              "priority": 4
            },
            {
              "address": "TUFdgdFjCoQefqNfamYPuyDsRkv471hs54",
              "chain_name": "Tron",
              "primary_category": "Sanctions",
              "secondary_category": "Prohibited Entity",
              "tertiary_category": "Huionepay",
              "quaternary_category": "huionepay-deposit",
              "risk_level": "high",
              "priority": 1
            },
            {
              "address": "TUFdgdFjCoQefqNfamYPuyDsRkv471hs54",
              "chain_name": "Tron",
              "primary_category": "Cybercrime",
              "secondary_category": "Black/Grey Industry",
              "tertiary_category": "Fraudsters",
              "quaternary_category": "fraudsters-address",
              "risk_level": "high",
              "priority": 4
            }
          ]
        },
        {
          "direction": -1,
          "request_id": 173378,
          "query_address": "TGE94jU39ithtHbrYAQJRTcvv785riPLdy",
          "chain_name": "Tron",
          "token": "usdt",
          "opponent_address": "TQuF**************************5RSa",
          "hops": 1,
          "path": [
            {
              "address": "TQuF**************************5RSa",
              "chain_name": "",
              "token": "",
              "deep": 0,
              "pre_address": "null",
              "tags": [
                {
                  "address": "TQuF**************************5RSa",
                  "chain_name": "Tron",
                  "primary_category": "Sanctions",
                  "secondary_category": "Prohibited Entity",
                  "tertiary_category": "Huionepay",
                  "quaternary_category": "huionepay-hotwallet",
                  "risk_level": "high",
                  "priority": 1
                },
                {
                  "address": "TQuF**************************5RSa",
                  "chain_name": "Tron",
                  "primary_category": "Sanctions",
                  "secondary_category": "Sanctioned Entity",
                  "tertiary_category": "Huionepay",
                  "quaternary_category": "huionepay-deposit",
                  "risk_level": "critical",
                  "priority": 4
                },
                {
                  "address": "TQuF**************************5RSa",
                  "chain_name": "Tron",
                  "primary_category": "Cybercrime",
                  "secondary_category": "Black/Grey Industry",
                  "tertiary_category": "Buying_hacker_data",
                  "quaternary_category": "buying_hacker_data-address",
                  "risk_level": "high",
                  "priority": 4
                }
              ],
              "amount": 0,
              "flag": 9,
              "last_closed_timestamp": 0
            },
            {
              "address": "TGE9**************************PLdy",
              "chain_name": "",
              "token": "",
              "deep": 0,
              "pre_address": "TQuF**************************5RSa",
              "tags": [
                {
                  "address": "TGE9**************************PLdy",
                  "chain_name": "Tron",
                  "primary_category": "Other Entities",
                  "secondary_category": "Wallet Address",
                  "tertiary_category": "Huionepay",
                  "quaternary_category": "huionepay-withdrawal-level1",
                  "risk_level": "low",
                  "priority": 4
                }
              ],
              "amount": 11195,
              "flag": 0,
              "last_closed_timestamp": 1746973572000
            }
          ],
          "tags": [
            {
              "address": "TQuFSvpct2FeBrKjRh8NDqtGAci2Z15RSa",
              "chain_name": "Tron",
              "primary_category": "Sanctions",
              "secondary_category": "Prohibited Entity",
              "tertiary_category": "Huionepay",
              "quaternary_category": "huionepay-hotwallet",
              "risk_level": "high",
              "priority": 1
            },
            {
              "address": "TQuFSvpct2FeBrKjRh8NDqtGAci2Z15RSa",
              "chain_name": "Tron",
              "primary_category": "Sanctions",
              "secondary_category": "Sanctioned Entity",
              "tertiary_category": "Huionepay",
              "quaternary_category": "huionepay-deposit",
              "risk_level": "critical",
              "priority": 4
            },
            {
              "address": "TQuFSvpct2FeBrKjRh8NDqtGAci2Z15RSa",
              "chain_name": "Tron",
              "primary_category": "Cybercrime",
              "secondary_category": "Black/Grey Industry",
              "tertiary_category": "Buying_hacker_data",
              "quaternary_category": "buying_hacker_data-address",
              "risk_level": "high",
              "priority": 4
            }
          ]
        },
        {
          "direction": -1,
          "request_id": 173378,
          "query_address": "TGE94jU39ithtHbrYAQJRTcvv785riPLdy",
          "chain_name": "Tron",
          "token": "usdt",
          "opponent_address": "TMqD**************************JczH",
          "hops": 1,
          "path": [
            {
              "address": "TMqD**************************JczH",
              "chain_name": "",
              "token": "",
              "deep": 0,
              "pre_address": "null",
              "tags": [
                {
                  "address": "TMqD**************************JczH",
                  "chain_name": "Tron",
                  "primary_category": "Sanctions",
                  "secondary_category": "Prohibited Entity",
                  "tertiary_category": "Huionepay",
                  "quaternary_category": "huionepay-hotwallet",
                  "risk_level": "high",
                  "priority": 1
                },
                {
                  "address": "TMqD**************************JczH",
                  "chain_name": "Tron",
                  "primary_category": "Sanctions",
                  "secondary_category": "Sanctioned Entity",
                  "tertiary_category": "Huionepay",
                  "quaternary_category": "huionepay-deposit",
                  "risk_level": "critical",
                  "priority": 4
                },
                {
                  "address": "TMqD**************************JczH",
                  "chain_name": "Tron",
                  "primary_category": "Cybercrime",
                  "secondary_category": "Black/Grey Industry",
                  "tertiary_category": "Buying_hacker_data",
                  "quaternary_category": "buying_hacker_data-address",
                  "risk_level": "high",
                  "priority": 4
                }
              ],
              "amount": 0,
              "flag": 9,
              "last_closed_timestamp": 0
            },
            {
              "address": "TGE9**************************PLdy",
              "chain_name": "",
              "token": "",
              "deep": 0,
              "pre_address": "TMqD**************************JczH",
              "tags": [
                {
                  "address": "TGE9**************************PLdy",
                  "chain_name": "Tron",
                  "primary_category": "Other Entities",
                  "secondary_category": "Wallet Address",
                  "tertiary_category": "Huionepay",
                  "quaternary_category": "huionepay-withdrawal-level1",
                  "risk_level": "low",
                  "priority": 4
                }
              ],
              "amount": 2188,
              "flag": 0,
              "last_closed_timestamp": 1741343109000
            }
          ],
          "tags": [
            {
              "address": "TMqDrZa5kEebg5wi3W3wusVZ6ZF2w6JczH",
              "chain_name": "Tron",
              "primary_category": "Cybercrime",
              "secondary_category": "Black/Grey Industry",
              "tertiary_category": "Buying_hacker_data",
              "quaternary_category": "buying_hacker_data-address",
              "risk_level": "high",
              "priority": 4
            },
            {
              "address": "TMqDrZa5kEebg5wi3W3wusVZ6ZF2w6JczH",
              "chain_name": "Tron",
              "primary_category": "Sanctions",
              "secondary_category": "Prohibited Entity",
              "tertiary_category": "Huionepay",
              "quaternary_category": "huionepay-hotwallet",
              "risk_level": "high",
              "priority": 1
            },
            {
              "address": "TMqDrZa5kEebg5wi3W3wusVZ6ZF2w6JczH",
              "chain_name": "Tron",
              "primary_category": "Sanctions",
              "secondary_category": "Sanctioned Entity",
              "tertiary_category": "Huionepay",
              "quaternary_category": "huionepay-deposit",
              "risk_level": "critical",
              "priority": 4
            }
          ]
        },
        {
          "direction": -1,
          "request_id": 173378,
          "query_address": "TGE94jU39ithtHbrYAQJRTcvv785riPLdy",
          "chain_name": "Tron",
          "token": "usdt",
          "opponent_address": "TCxu**************************omhr",
          "hops": 1,
          "path": [
            {
              "address": "TCxu**************************omhr",
              "chain_name": "",
              "token": "",
              "deep": 0,
              "pre_address": "null",
              "tags": [
                {
                  "address": "TCxu**************************omhr",
                  "chain_name": "Tron",
                  "primary_category": "Sanctions",
                  "secondary_category": "Prohibited Entity",
                  "tertiary_category": "Huionepay",
                  "quaternary_category": "huionepay-deposit",
                  "risk_level": "high",
                  "priority": 1
                },
                {
                  "address": "TCxu**************************omhr",
                  "chain_name": "Tron",
                  "primary_category": "Other Entities",
                  "secondary_category": "Wallet Address",
                  "tertiary_category": "Huionepay",
                  "quaternary_category": "huionepay-withdrawal-level1",
                  "risk_level": "low",
                  "priority": 4
                }
              ],
              "amount": 0,
              "flag": 1,
              "last_closed_timestamp": 0
            },
            {
              "address": "TGE9**************************PLdy",
              "chain_name": "",
              "token": "",
              "deep": 0,
              "pre_address": "TCxu**************************omhr",
              "tags": [
                {
                  "address": "TGE9**************************PLdy",
                  "chain_name": "Tron",
                  "primary_category": "Other Entities",
                  "secondary_category": "Wallet Address",
                  "tertiary_category": "Huionepay",
                  "quaternary_category": "huionepay-withdrawal-level1",
                  "risk_level": "low",
                  "priority": 4
                }
              ],
              "amount": 2000,
              "flag": 0,
              "last_closed_timestamp": 1739468781000
            }
          ],
          "tags": [
            {
              "address": "TCxurwX8hXg5YWm2iTAVU4tdho6qv8omhr",
              "chain_name": "Tron",
              "primary_category": "Sanctions",
              "secondary_category": "Prohibited Entity",
              "tertiary_category": "Huionepay",
              "quaternary_category": "huionepay-deposit",
              "risk_level": "high",
              "priority": 1
            },
            {
              "address": "TCxurwX8hXg5YWm2iTAVU4tdho6qv8omhr",
              "chain_name": "Tron",
              "primary_category": "Other Entities",
              "secondary_category": "Wallet Address",
              "tertiary_category": "Huionepay",
              "quaternary_category": "huionepay-withdrawal-level1",
              "risk_level": "low",
              "priority": 4
            }
          ]
        },
        {
          "direction": -1,
          "request_id": 173378,
          "query_address": "TGE94jU39ithtHbrYAQJRTcvv785riPLdy",
          "chain_name": "Tron",
          "token": "usdt",
          "opponent_address": "TCNK**************************32mM",
          "hops": 1,
          "path": [
            {
              "address": "TCNK**************************32mM",
              "chain_name": "",
              "token": "",
              "deep": 0,
              "pre_address": "null",
              "tags": [
                {
                  "address": "TCNK**************************32mM",
                  "chain_name": "Tron",
                  "primary_category": "Sanctions",
                  "secondary_category": "Prohibited Entity",
                  "tertiary_category": "Huionepay",
                  "quaternary_category": "huionepay-deposit",
                  "risk_level": "high",
                  "priority": 1
                },
                {
                  "address": "TCNK**************************32mM",
                  "chain_name": "Tron",
                  "primary_category": "Other Entities",
                  "secondary_category": "Wallet Address",
                  "tertiary_category": "Huionepay",
                  "quaternary_category": "huionepay-withdrawal-level1",
                  "risk_level": "low",
                  "priority": 4
                }
              ],
              "amount": 0,
              "flag": 1,
              "last_closed_timestamp": 0
            },
            {
              "address": "TGE9**************************PLdy",
              "chain_name": "",
              "token": "",
              "deep": 0,
              "pre_address": "TCNK**************************32mM",
              "tags": [
                {
                  "address": "TGE9**************************PLdy",
                  "chain_name": "Tron",
                  "primary_category": "Other Entities",
                  "secondary_category": "Wallet Address",
                  "tertiary_category": "Huionepay",
                  "quaternary_category": "huionepay-withdrawal-level1",
                  "risk_level": "low",
                  "priority": 4
                }
              ],
              "amount": 1000,
              "flag": 0,
              "last_closed_timestamp": 1734604641000
            }
          ],
          "tags": [
            {
              "address": "TCNKoCoYrA9LJ514Dex3WGEd66VYGX32mM",
              "chain_name": "Tron",
              "primary_category": "Other Entities",
              "secondary_category": "Wallet Address",
              "tertiary_category": "Huionepay",
              "quaternary_category": "huionepay-withdrawal-level1",
              "risk_level": "low",
              "priority": 4
            },
            {
              "address": "TCNKoCoYrA9LJ514Dex3WGEd66VYGX32mM",
              "chain_name": "Tron",
              "primary_category": "Sanctions",
              "secondary_category": "Prohibited Entity",
              "tertiary_category": "Huionepay",
              "quaternary_category": "huionepay-deposit",
              "risk_level": "high",
              "priority": 1
            }
          ]
        },
        {
          "direction": -1,
          "request_id": 173378,
          "query_address": "TGE94jU39ithtHbrYAQJRTcvv785riPLdy",
          "chain_name": "Tron",
          "token": "usdt",
          "opponent_address": "TFw3**************************yDV5",
          "hops": 1,
          "path": [
            {
              "address": "TFw3**************************yDV5",
              "chain_name": "",
              "token": "",
              "deep": 0,
              "pre_address": "null",
              "tags": [
                {
                  "address": "TFw3**************************yDV5",
                  "chain_name": "Tron",
                  "primary_category": "Sanctions",
                  "secondary_category": "Prohibited Entity",
                  "tertiary_category": "Huionepay",
                  "quaternary_category": "huionepay-deposit",
                  "risk_level": "high",
                  "priority": 1
                }
              ],
              "amount": 0,
              "flag": 1,
              "last_closed_timestamp": 0
            },
            {
              "address": "TGE9**************************PLdy",
              "chain_name": "",
              "token": "",
              "deep": 0,
              "pre_address": "TFw3**************************yDV5",
              "tags": [
                {
                  "address": "TGE9**************************PLdy",
                  "chain_name": "Tron",
                  "primary_category": "Other Entities",
                  "secondary_category": "Wallet Address",
                  "tertiary_category": "Huionepay",
                  "quaternary_category": "huionepay-withdrawal-level1",
                  "risk_level": "low",
                  "priority": 4
                }
              ],
              "amount": 5000,
              "flag": 0,
              "last_closed_timestamp": 1748663544000
            }
          ],
          "tags": [
            {
              "address": "TFw36HMK1bz4AK2LBd3nRhuPfJ5AEbyDV5",
              "chain_name": "Tron",
              "primary_category": "Sanctions",
              "secondary_category": "Prohibited Entity",
              "tertiary_category": "Huionepay",
              "quaternary_category": "huionepay-deposit",
              "risk_level": "high",
              "priority": 1
            }
          ]
        }
      ]
    },
    "msg": "success"
  }
}